README.md
setup.py
npcb/__init__.py
npcb.egg-info/PKG-INFO
npcb.egg-info/SOURCES.txt
npcb.egg-info/dependency_links.txt
npcb.egg-info/not-zip-safe
npcb.egg-info/requires.txt
npcb.egg-info/top_level.txt