Metadata-Version: 1.1
Name: npcb
Version: 0.0.1
Summary: Copy NumPy arrays via the clipboard
Home-page: https://github.com/MSeifert04/npcb
Author: Michael Seifert
Author-email: michaelseifert04@yahoo.de
License: Apache License 2.0
Keywords: funniest joke comedy flying circus
Platform: UNKNOWN
Classifier: Development Status :: 3 - Alpha
Classifier: License :: OSI Approved :: Apache Software License
Classifier: Programming Language :: Python
Classifier: Topic :: Text Processing :: Linguistic
